README.rst
setup.py
ctecLogstash/__init__.py
ctecLogstash/event.py
ctecLogstash/formatter.py
ctecLogstash/handler_amqp.py
ctecLogstash/handler_tcp.py
ctecLogstash/handler_udp.py
ctecLogstash.egg-info/PKG-INFO
ctecLogstash.egg-info/SOURCES.txt
ctecLogstash.egg-info/dependency_links.txt
ctecLogstash.egg-info/requires.txt
ctecLogstash.egg-info/top_level.txt
ctecLogstash/test/__init__.py
ctecLogstash/test/test_event.py