Metadata-Version: 1.1
Name: ctecLogstash
Version: 0.0.2
Summary: A python logstash project modify package which add appname
Home-page: https://github.com/kep-w/ec-logstash
Author: Kepner Wu
Author-email: kepner_wu@hotmail.com
License: MIT
Keywords: logstash python appname
Platform: all
Classifier: Development Status :: 4 - Beta
Classifier: Intended Audience :: Developers
Classifier: Topic :: Software Development :: Libraries
Classifier: License :: OSI Approved :: MIT License
Classifier: Programming Language :: Python :: 2.6
Classifier: Programming Language :: Python :: 2.7
Classifier: Programming Language :: Python :: 3
Classifier: Programming Language :: Python :: 3.3
Classifier: Programming Language :: Python :: 3.4
Classifier: Programming Language :: Python :: 3.5
